[{"website": "Null", "no_edu": "Null", "last_name": "Warner", "software_skills": "Python", "travel_from_university": "Null", "other_dietary": "Null", "linkedin": "Null", "dietary": "Null", "year": "3", "ethnicity": [{"S": "white"}], "reimbursement": "Null", "first_name": "John", "github": "Null", "user_id": "54c169f0-c1a4-3d65-8ffb-d1284bf47a54", "gender": "male", "university": "Psu", "travel_address": "Null", "cell": "4127158928", "age": "20", "shirt_size": "l", "hardware_skills": "None", "email": "jww6580@psu.edu", "first": "Null"}, {"website": "Michaelbailey.co", "no_edu": "Null", "last_name": "Bailey", "software_skills": "Python, Just won best use of AWS at a Hackathon, PHP, A lot of Linux including Bash, some JS, etc", "travel_from_university": true, "other_dietary": "Null", "linkedin": "LinkedIn.com/in/cybermichael", "dietary": "Null", "year": "1", "ethnicity": [{"S": "white"}], "reimbursement": "Null", "first_name": "Michael", "github": "GitHub.com/Mike-Bailey", "user_id": "212acaa1-bf74-3578-8a8b-9ee8f414b600", "gender": "male", "university": "George Mason University", "travel_address": "Null", "cell": "7032824029", "age": "18", "shirt_size": "l", "hardware_skills": "Raspberry Pi, Edison, Works in Infosec so networking protocols and stuff", "email": "mbae18@gmu.edu", "first": "Null"}, {"website": "Null", "no_edu": "Null", "last_name": "Kohli", "software_skills": "Java, C, JS, Node.js, Angular, Express, R", "travel_from_university": true, "other_dietary": "Null", "linkedin": "Null", "dietary": "Null", "year": "4", "ethnicity": [{"S": "asian"}], "reimbursement": "Null", "first_name": "Sahaj", "github": "Null", "user_id": "b984c635-332f-39c6-869e-9cc90d70d1ad", "gender": "male", "university": "Rutgers", "travel_address": "Null", "cell": "6099542409", "age": "22", "shirt_size": "l", "hardware_skills": "Rasberry Pi, Arduino", "email": "shjkohli@rutgers.edu", "first": "Null"}, {"website": "https://knaik94.github.io/", "no_edu": "Null", "last_name": "Naik", "software_skills": "Python, HTML5, Javascript, PHP, Java, Matlab", "travel_from_university": true, "mlh_coc": true, "linkedin": "Null", "dietary": [{"S": "vegetarian"}], "year": "4", "ethnicity": [{"S": "asian"}], "reimbursement": true, "first_name": "Karan", "github": "https://github.com/knaik94", "user_id": "e117d997-17d3-3400-9a31-14536dc86694", "gender": "male", "university": "Rutgers University", "travel_address": "Null", "cell": "7328234473", "age": "22", "other_dietary": "Null", "shirt_size": "l", "hardware_skills": "RaspberryPi, Myo Band", "email": "kn172@rutges.edu", "first": "Null"}, {"website": "Null", "no_edu": "Null", "last_name": "Dodley", "software_skills": "Python", "travel_from_university": true, "mlh_coc": true, "linkedin": "Null", "dietary": "Null", "year": "3", "ethnicity": [{"S": "asian"}], "reimbursement": "Null", "first_name": "Sanjana", "github": "Null", "user_id": "9522b993-44ee-342c-8c6c-ff99a23b1cb9", "gender": "female", "university": "Rutgers University - New Brunswick", "travel_address": "Null", "cell": "7327595223", "age": "20", "other_dietary": "Null", "shirt_size": "s", "hardware_skills": "Null", "email": "sanjana.dodley@scarletmail.rutgers.edu", "first": "Null"}, {"website": "Null", "no_edu": "Null", "last_name": "Garces", "software_skills": "Python, Java", "travel_from_university": true, "mlh_coc": true, "linkedin": "Null", "dietary": "Null", "year": "1", "ethnicity": [{"S": "hispanic"}], "reimbursement": true, "first_name": "Jordan", "github": "Null", "user_id": "a1cec43f-17a0-3231-9c53-8523dc759744", "gender": "male", "university": "RIT", "travel_address": "Null", "cell": "5184963312", "age": "18", "other_dietary": "Null", "shirt_size": "xl", "hardware_skills": "Circuit design, RasberryPi", "email": "jxg5057@gmail.com", "first": "Null"}, {"website": "Null", "no_edu": "Null", "last_name": "Patel", "software_skills": "Java, JavaScript, Angularjs, Nodejs, Python, HTML", "travel_from_university": true, "mlh_coc": true, "linkedin": "Null", "dietary": [{"S": "vegetarian"}], "year": "1", "ethnicity": [{"S": "asian"}], "reimbursement": true, "first_name": "Harsh", "github": "https://github.com/HershyKing", "user_id": "24a40a45-c4a2-313c-9633-e72bac424f70", "gender": "male", "university": "Temple University", "travel_address": "Null", "cell": "2154700100", "age": "18", "other_dietary": "Null", "shirt_size": "m", "hardware_skills": "Null", "email": "tug04320@temple.edi", "first": "Null"}, {"website": "Null", "no_edu": "Null", "last_name": "Chandrasekaran", "software_skills": "Python, AWS, C, C++, IBM Watson", "travel_from_university": true, "mlh_coc": true, "linkedin": "Null", "dietary": [{"S": "vegetarian"}], "year": "6", "ethnicity": [{"S": "asian"}], "reimbursement": true, "first_name": "Rishikanth", "github": "Null", "user_id": "5feb5630-bf6f-3a45-ae82-40bcef3f7133", "gender": "male", "university": "Columbia University", "travel_address": "Null", "cell": "3476155327", "age": "22", "other_dietary": "Null", "shirt_size": "s", "hardware_skills": "Raspberry Pi, BeagleBonr, Arduino, Spark, AVR. ARM", "email": "c.rishikanth@olumbia.edu", "first": "Null"}, {"website": "http://monmon-2007.github.io/mina-web/", "no_edu": "Null", "last_name": "Gadallah", "software_skills": "JAVA,Pyhton,CSS,HTML,C", "travel_from_university": true, "mlh_coc": true, "linkedin": "https://www.linkedin.com/in/mina-gadallah-0a8a5b88", "dietary": "Null", "year": "3", "ethnicity": [{"S": "white"}], "reimbursement": true, "first_name": "Mina", "github": "https://github.com/monmon-2007", "user_id": "65fdc9fb-7702-3237-a6e3-8ec9f7249369", "gender": "male", "university": "Rutgers University", "travel_address": "Null", "cell": "7322779164", "age": "22", "other_dietary": "Null", "shirt_size": "m", "hardware_skills": "arduino", "email": "mg7387@scarletmail.rutgers.edu", "first": "Null"}, {"website": "Null", "no_edu": "Null", "last_name": "Khurana", "software_skills": "Null", "travel_from_university": true, "mlh_coc": true, "linkedin": "Null", "dietary": [{"S": "vegetarian"}, {"S": "allergy_egg"}], "year": "2", "ethnicity": [{"S": "asian"}], "reimbursement": "Null", "first_name": "Jivtesh", "github": "Null", "user_id": "cb5ae471-3712-335a-8524-fa5e853e4631", "gender": "male", "university": "Penn State", "travel_address": "Null", "cell": "8145486581", "age": "20", "other_dietary": "Null", "shirt_size": "m", "hardware_skills": "Null", "email": "jbk5248@dce.psu.edu", "first": true}, {"website": "Null", "no_edu": "Null", "last_name": "Rhone", "software_skills": "Null", "travel_from_university": true, "mlh_coc": true, "linkedin": "Null", "dietary": "Null", "year": "3", "ethnicity": [{"S": "white"}], "reimbursement": "Null", "first_name": "Alex", "github": "Null", "user_id": "84b88d85-1a85-3ec9-9bc9-e877b127f3ad", "gender": "male", "university": "Penn State Harrisburg", "travel_address": "Null", "cell": "7174791871", "age": "22", "other_dietary": "Null", "shirt_size": "m", "hardware_skills": "Null", "email": "asr5215@psu.edi", "first": true}, {"website": "Null", "no_edu": "Null", "last_name": "Lim", "software_skills": "C++", "travel_from_university": true, "mlh_coc": true, "linkedin": "Null", "dietary": "Null", "year": "1", "ethnicity": [{"S": "asian"}], "reimbursement": "Null", "first_name": "Christian", "github": "Null", "user_id": "f931c1d1-15f9-3ff2-a5ec-82ef06b5f72c", "gender": "male", "university": "Penn state main", "travel_address": "Null", "cell": "2674320150", "age": "19", "other_dietary": "Null", "shirt_size": "m", "hardware_skills": "Null", "email": "cxl5525@psu.edu", "first": true}]